MANIFEST.in
README.md
setup.py
GF2Matrix/__init__.py
GF2Matrix/int_matrix.c
GF2Matrix/int_matrix.cp37-win_amd64.pyd
GF2Matrix/int_matrix.html
GF2Matrix/int_matrix.pyx
GF2Matrix.egg-info/PKG-INFO
GF2Matrix.egg-info/SOURCES.txt
GF2Matrix.egg-info/dependency_links.txt
GF2Matrix.egg-info/requires.txt
GF2Matrix.egg-info/top_level.txt
GF2Matrix/test/__init__.py
GF2Matrix/test/int_matrix_test.py